setup.py
sprintly_commit_parser/__init__.py
sprintly_commit_parser/commit_parser.py
sprintly_commit_parser.egg-info/PKG-INFO
sprintly_commit_parser.egg-info/SOURCES.txt
sprintly_commit_parser.egg-info/dependency_links.txt
sprintly_commit_parser.egg-info/not-zip-safe
sprintly_commit_parser.egg-info/top_level.txt