Metadata-Version: 1.0
Name: sprintly-commit-parser
Version: 0.1.0
Summary: Utility for parsing commits for Sprintly commands.
Home-page: https://github.com/sprintly/sprintly-commit-parser
Author: Nicholas Serra
Author-email: nserra@quickleft.com
License: BSD
Keywords: sprintly,commit,parser
Platform: UNKNOWN
Classifier: Programming Language :: Python
Classifier: Topic :: Software Development :: Libraries :: Python Modules
Classifier: Environment :: Web Environment
